example_bookmark_merger
setup
example
bookmark_pyparser
