Metadata-Version: 1.0
Name: bookmark-merger
Version: 0.2.2
Summary: code for merging multiple firefox bookmark.html files
Home-page: https://sourceforge.net/projects/bookmark-merger/
Author: robochat
Author-email: rjsteed@talk21.com
License: LGPLv3
Keywords: firefox
Platform: UNKNOWN
Classifier: License :: OSI Approved :: GNU Lesser General Public License v3 (LGPLv3)
Classifier: Programming Language :: Python
Classifier: Development Status :: 4 - Beta
Classifier: Environment :: Console
Classifier: Intended Audience :: Developers
Classifier: Intended Audience :: End Users/Desktop
Classifier: Intended Audience :: System Administrators
Classifier: Natural Language :: English
Classifier: Operating System :: OS Independent
Classifier: Topic :: Utilities
Classifier: Topic :: Internet :: WWW/HTTP :: Browsers
